README.rst
setup.py
boos/__init__.py
boos/boos.py
boos/cli.py
boos.egg-info/PKG-INFO
boos.egg-info/SOURCES.txt
boos.egg-info/dependency_links.txt
boos.egg-info/requires.txt
boos.egg-info/top_level.txt